volumio_websocket/__init__.py
volumio_websocket/__main__.py
volumio_websocket/api2websocket.py
volumio_websocket/websocket.py
volumio_websocket-1.0.15.dist-info/METADATA
volumio_websocket-1.0.15.dist-info/WHEEL
volumio_websocket-1.0.15.dist-info/top_level.txt
volumio_websocket-1.0.15.dist-info/RECORD
