Metadata-Version: 2.1
Name: volumio-websocket
Version: 1.0.15
Summary: Communicate with a volumio instance via websocket.
Home-page: https://github.com/Heiss/volumio_websocket
Author: Peter Heiss
Author-email: peter.heiss@uni-muenster.de
License: MIT
Platform: UNKNOWN
Classifier: License :: OSI Approved :: MIT License
Classifier: Programming Language :: Python :: 3
Classifier: Programming Language :: Python :: 3.8
Requires-Dist: python-socketio[asyncio_client]
